solana_account_sdk/__init__.py
solana_account_sdk/api.py
solana_account_sdk/core.py
solana_account_sdk/pyarmor_runtime_000000/__init__.py
solana_account_sdk/pyarmor_runtime_000000/pyarmor_runtime.pyd
solana_account_sdk-1.0.1.dist-info/METADATA
solana_account_sdk-1.0.1.dist-info/WHEEL
solana_account_sdk-1.0.1.dist-info/RECORD
