Metadata-Version: 2.1
Name: solana-account-sdk
Version: 1.0.1
Summary: 
Author: ws
Author-email: 123456789@gmail.com
Requires-Python: >=3.12,<4.0
Classifier: Programming Language :: Python :: 3
Classifier: Programming Language :: Python :: 3.12
Classifier: Programming Language :: Python :: 3.13
Requires-Dist: bip39 (>=0.0.2,<0.0.3)
Requires-Dist: mnemonic (>=0.21,<0.22)
Requires-Dist: pytoniq (>=0.1.40,<0.2.0)
Requires-Dist: solana (>=0.35.0,<0.36.0)
